sympyle/Node.py
sympyle/Tensor.py
sympyle/Utils.py
sympyle/__init__.py
sympyle/Ops/Add.py
sympyle/Ops/MSE.py
sympyle/Ops/Matmul.py
sympyle/Ops/Relu.py
sympyle/Ops/Sigmoid.py
sympyle/Ops/SoftmaxWithCrossEntropy.py
sympyle/Ops/Sub.py
sympyle/Ops/__init__.py
sympyle-0.0.12.dist-info/METADATA
sympyle-0.0.12.dist-info/RECORD
sympyle-0.0.12.dist-info/WHEEL
sympyle-0.0.12.dist-info/top_level.txt
