Metadata-Version: 2.1
Name: sympyle
Version: 0.0.12
Summary: Simple Automatic Differentiation in Python 
Home-page: https://github.com/harveyslash/sympyle
Author: Harshvardhan Gupta
Author-email: theharshvardhangupta@gmail.com
License: GNU GENERAL PUBLIC LICENSE
Platform: UNKNOWN
Requires-Dist: numpy
